{
  "greeting": "Hai",
  "name": "Eryn",
  "greetingText": "Hope you have a great day!",
  "wishText": "May Allah bless you with a long life! this is my sincere prayer to Allah on your birthday. Happy Birthday ;)",
  "imagePath": "img/eryn.jpg",
  "text1": "It's your birthday!!! :D",
  "textInChatBox": "Lagu Birthday nama eryn",
  "sendButtonLabel": "Send",
  "text2": "Tu yang aku nak buat",
  "text3": "Namun, disebabkan aku ni genius dan pintar.",
  "text4": "Aku dapat, Idea dan nak buat sedikit",
  "text4Adjective": "special",
  "text5Entry": "Sebab,",
  "text5Content": "Kereta kau special",
  "smiley": ":)",
  "bigTextPart1": "S",
  "bigTextPart2": "O",
  "wishHeading": "Happy Birthday!",
  "outroText": "Okay, nanti bagitau feedback.",
  "replayText": "atau click, kalau nak ulang dan terus ulang sampai abis keje",
  "outroSmiley": ":)"
}
